redwall/__init__.py
redwall/deviantart.py
redwall/getch.py
redwall/gfycat.py
redwall/reddit.py
redwall/reddit_objects.py
redwall/reddit_scraper.py
redwall/screensaver.py
redwall/set_wallpaper.py
redwall/url_util.py
redwall-0.1.1.dist-info/DESCRIPTION.rst
redwall-0.1.1.dist-info/METADATA
redwall-0.1.1.dist-info/RECORD
redwall-0.1.1.dist-info/WHEEL
redwall-0.1.1.dist-info/entry_points.txt
redwall-0.1.1.dist-info/metadata.json
redwall-0.1.1.dist-info/top_level.txt
