Metadata-Version: 2.0
Name: redwall
Version: 0.1.1
Summary: A reddit image/post scraper
Home-page: UNKNOWN
Author: Brett Settle
Author-email: brettjsettle@gmail.com
License: MIT
Platform: UNKNOWN
Classifier: Operating System :: OS Independent
Classifier: Programming Language :: Python
Classifier: Programming Language :: Python :: 3
Classifier: Programming Language :: Python :: 3.3
Classifier: Programming Language :: Python :: 3.4
Classifier: Programming Language :: Python :: 3.5
Classifier: Programming Language :: Python :: 3.6
Requires-Dist: beautifulsoup4
